pytoimage/__init__.py
pytoimage/pytoimage.py
pytoimage/fonts/Inconsolata.ttf
pytoimage-0.0.1.dist-info/LICENSE
pytoimage-0.0.1.dist-info/METADATA
pytoimage-0.0.1.dist-info/WHEEL
pytoimage-0.0.1.dist-info/top_level.txt
pytoimage-0.0.1.dist-info/RECORD
