Metadata-Version: 2.1
Name: pytoimage
Version: 0.0.1
Summary: Transform your Python code in an image.
Home-page: https://github.com/gabrielstork/pytoimage
Author: Gabriel Stork
Author-email: storkdeveloper@gmail.com
License: MIT
Keywords: image code custom theme color palette
Platform: UNKNOWN
Classifier: Development Status :: 3 - Alpha
Classifier: Programming Language :: Python :: 3
Classifier: License :: OSI Approved :: MIT License
Classifier: Operating System :: OS Independent
Requires-Python: >=3
License-File: LICENSE
